django_s3/__init__.py
django_s3-0.1.dist-info/DESCRIPTION.rst
django_s3-0.1.dist-info/METADATA
django_s3-0.1.dist-info/RECORD
django_s3-0.1.dist-info/WHEEL
django_s3-0.1.dist-info/metadata.json
django_s3-0.1.dist-info/top_level.txt
