Metadata-Version: 2.0
Name: django-s3
Version: 0.1
Summary: Simple S3 storage backend
Home-page: https://github.com/jochem/django-s3
Author: Jochem Oosterveen
Author-email: jochem@oosterveen.net
License: UNKNOWN
Keywords: django amazon s3
Platform: UNKNOWN
Requires-Dist: Django
Requires-Dist: boto3
